AUTHORS
CHANGELOG.txt
DESCRIPTION
LICENSE
MANIFEST.in
README.rst
setup.py
django_user_media.egg-info/PKG-INFO
django_user_media.egg-info/SOURCES.txt
django_user_media.egg-info/dependency_links.txt
django_user_media.egg-info/requires.txt
django_user_media.egg-info/top_level.txt
user_media/__init__.py
user_media/admin.py
user_media/compat.py
user_media/forms.py
user_media/models.py
user_media/processors.py
user_media/urls.py
user_media/views.py
user_media/migrations/0001_initial.py
user_media/migrations/0002_auto_20180105_1255.py
user_media/migrations/__init__.py
user_media/south_migrations/0001_initial.py
user_media/south_migrations/0002_auto__add_field_usermediaimage_position__chg_field_usermediaimage_imag.py
user_media/south_migrations/0003_auto__del_field_usermediaimage_position.py
user_media/south_migrations/0004_auto__add_field_usermediaimage_thumb_x__add_field_usermediaimage_thumb.py
user_media/south_migrations/__init__.py
user_media/static/user_media/css/libs/jquery.Jcrop.css
user_media/static/user_media/css/libs/jquery.fileupload-ui.css
user_media/static/user_media/img/Jcrop.gif
user_media/static/user_media/img/loading.gif
user_media/static/user_media/img/progressbar.gif
user_media/static/user_media/js/image_upload.js
user_media/static/user_media/js/jquery.fileupload-process.js
user_media/static/user_media/js/jquery.fileupload-ui.js
user_media/static/user_media/js/jquery.fileupload-validate.js
user_media/static/user_media/js/jquery.fileupload.js
user_media/static/user_media/js/tmpl.min.js
user_media/static/user_media/js/libs/jquery-1.9.1.js
user_media/static/user_media/js/libs/jquery-ui-1.10.3.custom.min.js
user_media/static/user_media/js/libs/jquery.Jcrop.js
user_media/static/user_media/js/libs/jquery.Jcrop.min.js
user_media/templates/user_media/usermediaimage_confirm_delete.html
user_media/templates/user_media/usermediaimage_form.html
user_media/templates/user_media/partials/ajax_usermediaimage_confirm_delete.html
user_media/templates/user_media/partials/ajax_usermediaimage_form.html
user_media/templates/user_media/partials/crop.html
user_media/templates/user_media/partials/image.html
user_media/templates/user_media/partials/image_upload.html
