Metadata-Version: 1.0
Name: django-user-media
Version: 1.2.5
Summary: A reusable app to graceously handle files that your users might upload, such
